{
	"info": {
		"_postman_id": "9f316d01-5430-4164-bce4-abc169c54825",
		"name": "AK7PD",
		"schema": "https://schema.getpostman.com/json/collection/v2.1.0/collection.json",
		"_exporter_id": "21917427"
	},
	"item": [
		{
			"name": "Users",
			"item": [
				{
					"name": "GetAll",
					"request": {
						"method": "GET",
						"header": [],
						"url": {
							"raw": "http://127.0.0.1:5000/users/getAll",
							"protocol": "http",
							"host": [
								"127",
								"0",
								"0",
								"1"
							],
							"port": "5000",
							"path": [
								"users",
								"getAll"
							]
						}
					},
					"response": []
				},
				{
					"name": "GetByName",
					"request": {
						"method": "GET",
						"header": [],
						"url": {
							"raw": "http://127.0.0.1:5000/users/getByName?name=main_guy",
							"protocol": "http",
							"host": [
								"127",
								"0",
								"0",
								"1"
							],
							"port": "5000",
							"path": [
								"users",
								"getByName"
							],
							"query": [
								{
									"key": "name",
									"value": "main_guy"
								}
							]
						}
					},
					"response": []
				},
				{
					"name": "GetById",
					"request": {
						"method": "GET",
						"header": [],
						"url": {
							"raw": "http://127.0.0.1:5000/users/getById?id=63c54df7d9246dd7a7da7e9f",
							"protocol": "http",
							"host": [
								"127",
								"0",
								"0",
								"1"
							],
							"port": "5000",
							"path": [
								"users",
								"getById"
							],
							"query": [
								{
									"key": "id",
									"value": "63c54df7d9246dd7a7da7e9f"
								}
							]
						}
					},
					"response": []
				},
				{
					"name": "FindUsers",
					"request": {
						"method": "GET",
						"header": [],
						"url": {
							"raw": "http://127.0.0.1:5000/users/findUsers",
							"protocol": "http",
							"host": [
								"127",
								"0",
								"0",
								"1"
							],
							"port": "5000",
							"path": [
								"users",
								"findUsers"
							],
							"query": [
								{
									"key": "firstName",
									"value": "Andrew",
									"disabled": true
								},
								{
									"key": "lastName",
									"value": "Moore",
									"disabled": true
								},
								{
									"key": "address",
									"value": "3243 Cedar Street, California, USA",
									"disabled": true
								},
								{
									"key": "socialNumber",
									"value": "5530133f6494h",
									"disabled": true
								},
								{
									"key": "sortBy",
									"value": "firstName",
									"disabled": true
								}
							]
						}
					},
					"response": []
				},
				{
					"name": "EditUser",
					"request": {
						"method": "POST",
						"header": [],
						"body": {
							"mode": "formdata",
							"formdata": [
								{
									"key": "username",
									"value": "test_user",
									"type": "text"
								},
								{
									"key": "password",
									"value": "123",
									"type": "text"
								},
								{
									"key": "firstName",
									"value": "test",
									"type": "text"
								},
								{
									"key": "lastName",
									"value": "test",
									"type": "text"
								},
								{
									"key": "socialNumber",
									"value": "123456789",
									"type": "text"
								},
								{
									"key": "address",
									"value": "asdasdasd",
									"type": "text"
								}
							]
						},
						"url": {
							"raw": "http://127.0.0.1:5000/users/editUser",
							"protocol": "http",
							"host": [
								"127",
								"0",
								"0",
								"1"
							],
							"port": "5000",
							"path": [
								"users",
								"editUser"
							]
						}
					},
					"response": []
				},
				{
					"name": "Create",
					"request": {
						"method": "POST",
						"header": [],
						"body": {
							"mode": "formdata",
							"formdata": [
								{
									"key": "userId",
									"value": "",
									"type": "text"
								},
								{
									"key": "username",
									"value": "test_user",
									"type": "text"
								},
								{
									"key": "password",
									"value": "123",
									"type": "text"
								},
								{
									"key": "firstName",
									"value": "test",
									"type": "text"
								},
								{
									"key": "lastName",
									"value": "test",
									"type": "text"
								},
								{
									"key": "socialNumber",
									"value": "123456789",
									"type": "text"
								},
								{
									"key": "address",
									"value": "asdasdasd",
									"type": "text"
								}
							]
						},
						"url": {
							"raw": "http://127.0.0.1:5000/users/create",
							"protocol": "http",
							"host": [
								"127",
								"0",
								"0",
								"1"
							],
							"port": "5000",
							"path": [
								"users",
								"create"
							]
						}
					},
					"response": []
				}
			]
		},
		{
			"name": "Books",
			"item": [
				{
					"name": "GetAll",
					"request": {
						"method": "GET",
						"header": [],
						"url": {
							"raw": "http://127.0.0.1:5000/books/getAll",
							"protocol": "http",
							"host": [
								"127",
								"0",
								"0",
								"1"
							],
							"port": "5000",
							"path": [
								"books",
								"getAll"
							]
						}
					},
					"response": []
				},
				{
					"name": "GetByTitle",
					"request": {
						"method": "GET",
						"header": [],
						"url": {
							"raw": "http://127.0.0.1:5000/books/getByTitle?title=Catch-22",
							"protocol": "http",
							"host": [
								"127",
								"0",
								"0",
								"1"
							],
							"port": "5000",
							"path": [
								"books",
								"getByTitle"
							],
							"query": [
								{
									"key": "title",
									"value": "Catch-22"
								}
							]
						}
					},
					"response": []
				},
				{
					"name": "GetById",
					"request": {
						"method": "GET",
						"header": [],
						"url": {
							"raw": "http://127.0.0.1:5000/books/getById?id=63c54df6d9246dd7a7da7e8f",
							"protocol": "http",
							"host": [
								"127",
								"0",
								"0",
								"1"
							],
							"port": "5000",
							"path": [
								"books",
								"getById"
							],
							"query": [
								{
									"key": "id",
									"value": "63c54df6d9246dd7a7da7e8f"
								}
							]
						}
					},
					"response": []
				},
				{
					"name": "FindUsers Copy",
					"request": {
						"method": "GET",
						"header": [],
						"url": {
							"raw": "http://127.0.0.1:5000/users/findUsers",
							"protocol": "http",
							"host": [
								"127",
								"0",
								"0",
								"1"
							],
							"port": "5000",
							"path": [
								"users",
								"findUsers"
							],
							"query": [
								{
									"key": "firstName",
									"value": "Andrew",
									"disabled": true
								},
								{
									"key": "lastName",
									"value": "Moore",
									"disabled": true
								},
								{
									"key": "address",
									"value": "3243 Cedar Street, California, USA",
									"disabled": true
								},
								{
									"key": "socialNumber",
									"value": "5530133f6494h",
									"disabled": true
								},
								{
									"key": "sortBy",
									"value": "firstName",
									"disabled": true
								}
							]
						}
					},
					"response": []
				},
				{
					"name": "Create",
					"request": {
						"method": "POST",
						"header": [
							{
								"key": "username",
								"value": "",
								"type": "text"
							},
							{
								"key": "password",
								"value": "",
								"type": "text"
							},
							{
								"key": "first_name",
								"value": "",
								"type": "text"
							},
							{
								"key": "last_name",
								"value": "",
								"type": "text"
							},
							{
								"key": "social_number",
								"value": "",
								"type": "text"
							},
							{
								"key": "address",
								"value": "",
								"type": "text"
							},
							{
								"key": "name",
								"value": "",
								"type": "text"
							}
						],
						"url": {
							"raw": "http://127.0.0.1:5000/books/create",
							"protocol": "http",
							"host": [
								"127",
								"0",
								"0",
								"1"
							],
							"port": "5000",
							"path": [
								"books",
								"create"
							]
						}
					},
					"response": []
				},
				{
					"name": "UploadPicture",
					"request": {
						"method": "POST",
						"header": [
							{
								"key": "userId",
								"value": "",
								"type": "text"
							}
						],
						"body": {
							"mode": "file",
							"file": {}
						},
						"url": {
							"raw": "http://127.0.0.1:5000/users/editUser",
							"protocol": "http",
							"host": [
								"127",
								"0",
								"0",
								"1"
							],
							"port": "5000",
							"path": [
								"users",
								"editUser"
							]
						}
					},
					"response": []
				}
			]
		},
		{
			"name": "Loans",
			"item": [
				{
					"name": "GetAll",
					"request": {
						"method": "GET",
						"header": [],
						"url": {
							"raw": "http://127.0.0.1:5000/loans/getAll",
							"protocol": "http",
							"host": [
								"127",
								"0",
								"0",
								"1"
							],
							"port": "5000",
							"path": [
								"loans",
								"getAll"
							]
						}
					},
					"response": []
				},
				{
					"name": "GetByUserId",
					"request": {
						"method": "GET",
						"header": [],
						"url": {
							"raw": "http://127.0.0.1:5000/loans/getByUserId?userId=63c54df7d9246dd7a7da7e9f",
							"protocol": "http",
							"host": [
								"127",
								"0",
								"0",
								"1"
							],
							"port": "5000",
							"path": [
								"loans",
								"getByUserId"
							],
							"query": [
								{
									"key": "userId",
									"value": "63c54df7d9246dd7a7da7e9f"
								}
							]
						}
					},
					"response": []
				},
				{
					"name": "GetActiveLoans",
					"request": {
						"method": "GET",
						"header": [],
						"url": {
							"raw": "http://127.0.0.1:5000/loans/getActiveLoans?userId",
							"protocol": "http",
							"host": [
								"127",
								"0",
								"0",
								"1"
							],
							"port": "5000",
							"path": [
								"loans",
								"getActiveLoans"
							],
							"query": [
								{
									"key": "userId",
									"value": null
								}
							]
						}
					},
					"response": []
				},
				{
					"name": "Create",
					"request": {
						"method": "POST",
						"header": [
							{
								"key": "username",
								"value": "",
								"type": "text"
							},
							{
								"key": "password",
								"value": "",
								"type": "text"
							},
							{
								"key": "first_name",
								"value": "",
								"type": "text"
							},
							{
								"key": "last_name",
								"value": "",
								"type": "text"
							},
							{
								"key": "social_number",
								"value": "",
								"type": "text"
							},
							{
								"key": "address",
								"value": "",
								"type": "text"
							},
							{
								"key": "name",
								"value": "",
								"type": "text"
							}
						],
						"url": {
							"raw": "http://127.0.0.1:5000/loans/create",
							"protocol": "http",
							"host": [
								"127",
								"0",
								"0",
								"1"
							],
							"port": "5000",
							"path": [
								"loans",
								"create"
							]
						}
					},
					"response": []
				}
			]
		},
		{
			"name": "Admin",
			"item": [
				{
					"name": "ExportDb",
					"request": {
						"method": "GET",
						"header": [],
						"url": {
							"raw": "http://127.0.0.1:5000/admin/exportDb",
							"protocol": "http",
							"host": [
								"127",
								"0",
								"0",
								"1"
							],
							"port": "5000",
							"path": [
								"admin",
								"exportDb"
							]
						}
					},
					"response": []
				},
				{
					"name": "ImportDb",
					"protocolProfileBehavior": {
						"disableBodyPruning": true
					},
					"request": {
						"method": "GET",
						"header": [],
						"body": {
							"mode": "file",
							"file": {}
						},
						"url": {
							"raw": "http://127.0.0.1:5000/admin/importDb",
							"protocol": "http",
							"host": [
								"127",
								"0",
								"0",
								"1"
							],
							"port": "5000",
							"path": [
								"admin",
								"importDb"
							]
						}
					},
					"response": []
				},
				{
					"name": "ActivateUser",
					"request": {
						"method": "GET",
						"header": [],
						"url": {
							"raw": "http://127.0.0.1:5000/admin/activateUser",
							"protocol": "http",
							"host": [
								"127",
								"0",
								"0",
								"1"
							],
							"port": "5000",
							"path": [
								"admin",
								"activateUser"
							]
						}
					},
					"response": []
				}
			]
		},
		{
			"name": "Login",
			"request": {
				"method": "POST",
				"header": [],
				"body": {
					"mode": "formdata",
					"formdata": [
						{
							"key": "username",
							"value": "main_guy",
							"type": "text"
						},
						{
							"key": "password",
							"value": "1234",
							"type": "text"
						}
					]
				},
				"url": {
					"raw": "http://127.0.0.1:5000/login",
					"protocol": "http",
					"host": [
						"127",
						"0",
						"0",
						"1"
					],
					"port": "5000",
					"path": [
						"login"
					]
				}
			},
			"response": []
		},
		{
			"name": "Logout",
			"request": {
				"method": "GET",
				"header": [],
				"url": {
					"raw": "http://127.0.0.1:5000/logout",
					"protocol": "http",
					"host": [
						"127",
						"0",
						"0",
						"1"
					],
					"port": "5000",
					"path": [
						"logout"
					]
				}
			},
			"response": []
		}
	]
}